Metadata-Version: 2.1
Name: effective-horizon
Version: 0.1.3
Summary: Code for the NeurIPS 2023 paper "Bridging RL Theory and Practice with the Effective horizon" and the ICLR 2024 paper "The Effective Horizon Explains Deep RL Performance in Stochastic Environments".
Author-email: Cassidy Laidlaw <cassidy_laidlaw@berkeley.edu>
Project-URL: Homepage, https://github.com/cassidylaidlaw/effective-horizon
Classifier: Development Status :: 3 - Alpha
Classifier: Intended Audience :: Science/Research
Classifier: Topic :: Scientific/Engineering :: Artificial Intelligence
Classifier: License :: OSI Approved :: MIT License
Classifier: Programming Language :: Python :: 3
Classifier: Programming Language :: Python :: 3.8
Classifier: Programming Language :: Python :: 3.9
Classifier: Programming Language :: Python :: 3.10
Requires-Python: >=3.8
Requires-Dist: sacred >=0.8.2
Requires-Dist: torch >=1.10.0
Requires-Dist: minigrid <2.3,>=2.2
Requires-Dist: gymnasium[atari]
Requires-Dist: numpy >=1.20.3
Requires-Dist: scipy >=1.8
Requires-Dist: autorom[accept-rom-license] >=0.4.2
Requires-Dist: GPUtil >=1.4.0
Requires-Dist: procgen >=0.10.7
Requires-Dist: torchvision >=0.11.1
Requires-Dist: tensorflow-probability
Requires-Dist: tqdm
Requires-Dist: opencv-python
Requires-Dist: tensorboard
Provides-Extra: dev
Requires-Dist: black ; extra == 'dev'
Requires-Dist: flake8 ; extra == 'dev'
Requires-Dist: pep8-naming ; extra == 'dev'
Requires-Dist: mypy ; extra == 'dev'
Requires-Dist: pytest ; extra == 'dev'
Requires-Dist: pytest-timeout ; extra == 'dev'
Requires-Dist: pytest-xdist ; extra == 'dev'
Requires-Dist: pytest-notebook ; extra == 'dev'
Requires-Dist: isort ; extra == 'dev'
Requires-Dist: types-psutil ; extra == 'dev'
Requires-Dist: ipykernel ; extra == 'dev'
Provides-Extra: rllib
Requires-Dist: ray[rllib] <2.6,>=2.5 ; extra == 'rllib'
Provides-Extra: sb3
Requires-Dist: stable-baselines3 ==2.2.1 ; extra == 'sb3'
Requires-Dist: imitation ==1.0.0 ; extra == 'sb3'
